[[{"url":"twittertv.com", "count":4}, {"url":"fbtv.com", "count":1},{"url":"abctv.com", "count":5},{"url":"football.com", "count":3},{"url":"score.com", "count":3}], [{"url":"scene.com", "count":5},{"url":"keeper.com", "count":3}],[{"url":"triptv.com", "count":4}, {"url":"fbtv.com", "count":1},{"url":"abctv.com", "count":5},{"url":"click.com", "count":3},{"url":"count.com", "count":3}],[{"url":"twittertv.com", "count":4}, {"url":"cbstv.com", "count":1},{"url":"fiiker.com", "count":5},{"url":"kick.com", "count":3},{"url":"score.com", "count":3}], [{"url":"scene.com", "count":5},{"url":"keeper.com", "count":3}],[]]
